README.rst
setup.cfg
setup.py
flotilla/__init__.py
flotilla/datapackage.py
flotilla/study.py
flotilla/util.py
flotilla.egg-info/PKG-INFO
flotilla.egg-info/SOURCES.txt
flotilla.egg-info/dependency_links.txt
flotilla.egg-info/requires.txt
flotilla.egg-info/top_level.txt
flotilla/compute/__init__.py
flotilla/compute/decomposition.py
flotilla/compute/expression.py
flotilla/compute/generic.py
flotilla/compute/infotheory.py
flotilla/compute/network.py
flotilla/compute/outlier.py
flotilla/compute/predict.py
flotilla/compute/splicing.py
flotilla/data_model/__init__.py
flotilla/data_model/base.py
flotilla/data_model/expression.py
flotilla/data_model/gene_ontology.py
flotilla/data_model/metadata.py
flotilla/data_model/quality_control.py
flotilla/data_model/splicing.py
flotilla/data_model/supplemental.py
flotilla/external/__init__.py
flotilla/external/combat.py
flotilla/test/__init__.py
flotilla/test/conftest.py
flotilla/test/test_datapackage.py
flotilla/test/test_embark.py
flotilla/test/test_study.py
flotilla/test/test_util.py
flotilla/visualize/__init__.py
flotilla/visualize/color.py
flotilla/visualize/decomposition.py
flotilla/visualize/expression.py
flotilla/visualize/gene_ontology.py
flotilla/visualize/generic.py
flotilla/visualize/ipython_interact.py
flotilla/visualize/network.py
flotilla/visualize/predict.py
flotilla/visualize/splicing.py