Metadata-Version: 1.1
Name: flotilla
Version: 0.3.2
Summary: Embark on a journey of single-cell data exploration.
Home-page: http://github.com/YeoLab/flotilla
Author: olgabot
Author-email: olgabot@ucsd.edu
License: 3-Clause BSD
Platform: UNKNOWN
Classifier: License :: OSI Approved :: BSD License
Classifier: Topic :: Scientific/Engineering :: Bio-Informatics
Classifier: Topic :: Scientific/Engineering :: Visualization
Classifier: Topic :: Scientific/Engineering :: Medical Science Apps.
Classifier: Programming Language :: Python :: 2.7
Classifier: Topic :: Multimedia :: Graphics
Classifier: Operating System :: POSIX
Classifier: Operating System :: Unix
Classifier: Operating System :: MacOS
Classifier: Operating System :: Microsoft :: Windows
